{
  "attack_focus": {
    "id": "attack_focus",
    "name": "Attack Focus",
    "description": "Increase Attack by 10%.",
    "effects": [
      {
        "type": "stat_boost",
        "stat": "attack",
        "value": 0.1
      }
    ]
  },
  "defense_focus": {
    "id": "defense_focus",
    "name": "Defense Focus",
    "description": "Increase Defense by 10%.",
    "effects": [
      {
        "type": "stat_boost",
        "stat": "defense",
        "value": 0.1
      }
    ]
  },
  "health_focus": {
    "id": "health_focus",
    "name": "Health Focus",
    "description": "Increase Health by 10%.",
    "effects": [
      {
        "type": "stat_boost",
        "stat": "health",
        "value": 0.1
      }
    ]
  },
  "healing_waters": {
    "id": "healing_waters",
    "name": "Healing Waters",
    "description": "30% of water damage done will also heal the spirit.",
    "effects": [
      {
        "type": "elemental_lifesteal",
        "element": "water",
        "ratio": 0.3
      }
    ]
  },
  "healing_flames": {
    "id": "healing_flames",
    "name": "Healing Flames",
    "description": "30% of fire damage done will also heal the spirit.",
    "effects": [
      {
        "type": "elemental_lifesteal",
        "element": "fire",
        "ratio": 0.3
      }
    ]
  },
  "poison_thorns": {
    "id": "poison_thorns",
    "name": "Poison Thorns",
    "description": "Attackers that damage this spirit become poisoned for 5 turns.",
    "effects": [
      {
        "type": "dot_attacker",
        "damageRatio": 0.125,
        "duration": 5
      }
    ]
  },
  "crit_mastery": {
    "id": "crit_mastery",
    "name": "Crit Mastery",
    "description": "Grants 20% Critical Hit Chance.",
    "effects": [
      {
        "type": "crit_chance_boost",
        "value": 0.2
      }
    ]
  },
  "dot_amplification": {
    "id": "dot_amplification",
    "name": "DoT Amplification",
    "description": "Increases Damage-over-Time dealt by 30%.",
    "effects": [
      {
        "type": "dot_damage_boost",
        "value": 0.3
      }
    ]
  },
  "damage_reflect": {
    "id": "damage_reflect",
    "name": "Stone Scale",
    "description": "Reflects 15% of all incoming damage back to the attacker.",
    "effects": [
      {
        "type": "damage_reflect_passive",
        "ratio": 0.15
      }
    ]
  },
  "counter_strike": {
    "id": "counter_strike",
    "name": "Counter Strike",
    "description": "50% chance to immediately counter-attack with a basic attack when hit.",
    "effects": [
      {
        "type": "counter_attack_chance",
        "chance": 0.5
      }
    ]
  },
  "lucky": {
    "id": "lucky",
    "name": "Lucky",
    "description": "Increases critical hit chance and status effect application by 10%.",
    "effects": [
      {
        "type": "chance_boost",
        "value": 0.1
      }
    ]
  },
  "regenerative": {
    "id": "regenerative",
    "name": "Regenerative",
    "description": "Recovers 25% of max health when swapped out of battle.",
    "effects": [
      {
        "type": "swap_out_heal",
        "healPercentage": 0.25
      }
    ]
  },
  "stalwart": {
    "id": "stalwart",
    "name": "Stalwart",
    "description": "This spirit cannot receive critical hits.",
    "effects": [
      {
        "type": "crit_immunity"
      }
    ]
  },
  "strategic": {
    "id": "strategic",
    "name": "Strategic",
    "description": "Increase Attack when going second.",
    "effects": []
  }
}
